dmx/__init__.py
dmx/arithmetic.py
dmx/bexamples/dpm_auto_example1.py
dmx/bexamples/dpm_auto_example2.py
dmx/bstats/__init__.py
dmx/bstats/bernoulli.py
dmx/bstats/bestimation.py
dmx/bstats/beta.py
dmx/bstats/catdirichlet.py
dmx/bstats/categorical.py
dmx/bstats/composite.py
dmx/bstats/conditional.py
dmx/bstats/dirac.py
dmx/bstats/dirichlet.py
dmx/bstats/dmvn.py
dmx/bstats/dpm.py
dmx/bstats/exponential.py
dmx/bstats/gamma.py
dmx/bstats/gaussian.py
dmx/bstats/geometric.py
dmx/bstats/ignored.py
dmx/bstats/intrange.py
dmx/bstats/mixture.py
dmx/bstats/mvngamma.py
dmx/bstats/normgamma.py
dmx/bstats/nulldist.py
dmx/bstats/optional.py
dmx/bstats/pdist.py
dmx/bstats/poisson.py
dmx/bstats/sequence.py
dmx/bstats/setdist.py
dmx/bstats/symdirichlet.py
dmx/mpi4py/bstats/__init__.py
dmx/mpi4py/stats/__init__.py
dmx/mpi4py/utils/automatic.py
dmx/mpi4py/utils/bestimation.py
dmx/mpi4py/utils/estimation.py
dmx/mpi4py/utils/humap.py
dmx/mpi4py/utils/optsutil.py
dmx/stats/__init__.py
dmx/stats/binomial.py
dmx/stats/categorical.py
dmx/stats/catmultinomial.py
dmx/stats/composite.py
dmx/stats/conditional.py
dmx/stats/dirac_length.py
dmx/stats/dirichlet.py
dmx/stats/dmvn.py
dmx/stats/dmvn_mixture.py
dmx/stats/exponential.py
dmx/stats/gamma.py
dmx/stats/gaussian.py
dmx/stats/geometric.py
dmx/stats/gmm.py
dmx/stats/heterogeneous_mixture.py
dmx/stats/hidden_association.py
dmx/stats/hidden_markov.py
dmx/stats/hmixture.py
dmx/stats/icltree.py
dmx/stats/ignored.py
dmx/stats/int_edit_setdist.py
dmx/stats/int_edit_stepsetdist.py
dmx/stats/int_hidden_association.py
dmx/stats/int_markovchain.py
dmx/stats/int_plsi.py
dmx/stats/int_spike.py
dmx/stats/intmultinomial.py
dmx/stats/intrange.py
dmx/stats/intsetdist.py
dmx/stats/jmixture.py
dmx/stats/lda.py
dmx/stats/log_gaussian.py
dmx/stats/look_back_hmm.py
dmx/stats/markovchain.py
dmx/stats/mixture.py
dmx/stats/mvn.py
dmx/stats/null_dist.py
dmx/stats/optional.py
dmx/stats/pdist.py
dmx/stats/poisson.py
dmx/stats/rdd_sampler.py
dmx/stats/select.py
dmx_learn-1.0.0.dist-info/licenses/LICENSE
dmx_learn-1.0.0.dist-info/METADATA
dmx_learn-1.0.0.dist-info/WHEEL
dmx_learn-1.0.0.dist-info/top_level.txt
dmx_learn-1.0.0.dist-info/RECORD
