Metadata-Version: 2.4
Name: dmx-learn
Version: 1.0.0
Summary: A package for estimating heterogeneous probability density functions.
Author: Adam Walder
License: BSD
Keywords: machine learning,density estimation,statistics,heterogeneous data
Classifier: Programming Language :: Python
Classifier: Development Status :: 4 - Beta
Classifier: Intended Audience :: Developers
Requires-Python: >=3.10
License-File: LICENSE
Requires-Dist: mpmath
Requires-Dist: numba
Requires-Dist: numpy
Requires-Dist: pandas
Requires-Dist: pyspark
Requires-Dist: scipy
Provides-Extra: test
Requires-Dist: pytest; extra == "test"
Provides-Extra: optional
Requires-Dist: mpi4py; extra == "optional"
Requires-Dist: umap-learn; extra == "optional"
Dynamic: license-file
